{
 "aggregate_function_based_on": "",
 "background_color": "#F9E795",
 "color": "#000000",
 "creation": "2025-12-11 12:17:28.248054",
 "currency": "",
 "docstatus": 0,
 "doctype": "Number Card",
 "document_type": "Project",
 "dynamic_filters_json": "{}",
 "filters_json": "{}",
 "function": "Count",
 "idx": 0,
 "is_public": 1,
 "is_standard": 1,
 "label": "Primary Reviewer's Projects",
 "method": "sirb.api.get_primary_reviewer_unapproved_project_count",
 "modified": "2025-12-11 12:40:40.093964",
 "modified_by": "Administrator",
 "module": "Sirb",
 "name": "Primary Reviewer's Projects",
 "owner": "Administrator",
 "parent_document_type": "",
 "report_function": "Sum",
 "report_name": "",
 "show_percentage_stats": 1,
 "stats_time_interval": "Daily",
 "type": "Custom"
}